sm_dag_compiler/__init__.py
sm_dag_compiler/__version__.py
sm_dag_compiler/api/__init__.py
sm_dag_compiler/api/dag/__init__.py
sm_dag_compiler/api/dag/base_dag.py
sm_dag_compiler/api/dag/edge_types.py
sm_dag_compiler/api/dag/enhanced_dag.py
sm_dag_compiler/cli/__init__.py
sm_dag_compiler/core/__init__.py
sm_dag_compiler/core/assembler/__init__.py
sm_dag_compiler/core/assembler/pipeline_assembler.py
sm_dag_compiler/core/assembler/pipeline_template_base.py
sm_dag_compiler/core/base/__init__.py
sm_dag_compiler/core/base/builder_base.py
sm_dag_compiler/core/base/config_base.py
sm_dag_compiler/core/base/contract_base.py
sm_dag_compiler/core/base/enums.py
sm_dag_compiler/core/base/hyperparameters_base.py
sm_dag_compiler/core/base/specification_base.py
sm_dag_compiler/core/compiler/__init__.py
sm_dag_compiler/core/compiler/config_resolver.py
sm_dag_compiler/core/compiler/dag_compiler.py
sm_dag_compiler/core/compiler/dynamic_template.py
sm_dag_compiler/core/compiler/exceptions.py
sm_dag_compiler/core/compiler/name_generator.py
sm_dag_compiler/core/compiler/validation.py
sm_dag_compiler/core/config_fields/__init__.py
sm_dag_compiler/core/config_fields/circular_reference_tracker.py
sm_dag_compiler/core/config_fields/config_class_detector.py
sm_dag_compiler/core/config_fields/config_class_store.py
sm_dag_compiler/core/config_fields/config_field_categorizer.py
sm_dag_compiler/core/config_fields/config_merger.py
sm_dag_compiler/core/config_fields/constants.py
sm_dag_compiler/core/config_fields/type_aware_config_serializer.py
sm_dag_compiler/core/deps/__init__.py
sm_dag_compiler/core/deps/base_specifications.py
sm_dag_compiler/core/deps/dependency_resolver.py
sm_dag_compiler/core/deps/factory.py
sm_dag_compiler/core/deps/property_reference.py
sm_dag_compiler/core/deps/registry_manager.py
sm_dag_compiler/core/deps/semantic_matcher.py
sm_dag_compiler/core/deps/specification_registry.py
sm_dag_compiler/steps/__init__.py
sm_dag_compiler/steps/builders/__init__.py
sm_dag_compiler-1.0.1.dist-info/licenses/LICENSE
sm_dag_compiler-1.0.1.dist-info/METADATA
sm_dag_compiler-1.0.1.dist-info/WHEEL
sm_dag_compiler-1.0.1.dist-info/entry_points.txt
sm_dag_compiler-1.0.1.dist-info/top_level.txt
sm_dag_compiler-1.0.1.dist-info/RECORD
