Metadata-Version: 2.4
Name: sm-dag-compiler
Version: 1.0.1
Summary: Automatic SageMaker Pipeline Generation from DAG Specifications
Author-email: Tianpei Xie <unidoctor@gmail.com>
Maintainer-email: Tianpei Xie <unidoctor@gmail.com>
License-Expression: MIT
Project-URL: Homepage, https://github.com/TianpeiLuke/sm-dag-compiler
Project-URL: Documentation, https://github.com/TianpeiLuke/sm-dag-compiler/blob/main/README.md
Project-URL: Repository, https://github.com/TianpeiLuke/sm-dag-compiler
Project-URL: Issues, https://github.com/TianpeiLuke/sm-dag-compiler/issues
Project-URL: Changelog, https://github.com/TianpeiLuke/sm-dag-compiler/blob/main/CHANGELOG.md
Keywords: sagemaker,pipeline,dag,machine-learning,aws,automation,mlops,data-science,workflow,orchestration
Classifier: Development Status :: 5 - Production/Stable
Classifier: Intended Audience :: Developers
Classifier: Intended Audience :: Science/Research
Classifier: Intended Audience :: Information Technology
Classifier: Operating System :: OS Independent
Classifier: Programming Language :: Python :: 3
Classifier: Programming Language :: Python :: 3.8
Classifier: Programming Language :: Python :: 3.9
Classifier: Programming Language :: Python :: 3.10
Classifier: Programming Language :: Python :: 3.11
Classifier: Programming Language :: Python :: 3.12
Classifier: Topic :: Scientific/Engineering :: Artificial Intelligence
Classifier: Topic :: Software Development :: Libraries :: Python Modules
Classifier: Topic :: System :: Distributed Computing
Classifier: Framework :: AWS CDK
Requires-Python: >=3.8
License-File: LICENSE
Requires-Dist: boto3>=1.39.0
Requires-Dist: botocore>=1.39.0
Requires-Dist: sagemaker>=2.248.0
Requires-Dist: pydantic>=2.11.0
Requires-Dist: PyYAML>=6.0.0
Requires-Dist: networkx>=3.5.0
Requires-Dist: click>=8.2.0
Requires-Dist: requests>=2.32.0
Requires-Dist: packaging>=24.2.0
Requires-Dist: typing_extensions>=4.14.0
Requires-Dist: pandas>=2.1.0
Requires-Dist: numpy>=1.26.0
Requires-Dist: scikit-learn>=1.3.0
Requires-Dist: joblib>=1.5.0
Requires-Dist: xgboost>=2.0.0
Requires-Dist: matplotlib>=3.8.0
Provides-Extra: pytorch
Requires-Dist: torch>=2.0.0; extra == "pytorch"
Requires-Dist: pytorch-lightning>=2.0.0; extra == "pytorch"
Requires-Dist: torchmetrics>=1.0.0; extra == "pytorch"
Requires-Dist: lightning>=2.0.0; extra == "pytorch"
Provides-Extra: xgboost
Requires-Dist: xgboost>=2.0.0; extra == "xgboost"
Requires-Dist: scikit-learn>=1.3.0; extra == "xgboost"
Requires-Dist: pandas>=2.0.0; extra == "xgboost"
Requires-Dist: numpy>=1.24.0; extra == "xgboost"
Provides-Extra: nlp
Requires-Dist: transformers>=4.30.0; extra == "nlp"
Requires-Dist: spacy>=3.7.0; extra == "nlp"
Requires-Dist: tokenizers>=0.15.0; extra == "nlp"
Requires-Dist: huggingface-hub>=0.20.0; extra == "nlp"
Provides-Extra: processing
Requires-Dist: pandas>=2.0.0; extra == "processing"
Requires-Dist: numpy>=1.24.0; extra == "processing"
Requires-Dist: scipy>=1.10.0; extra == "processing"
Requires-Dist: pyarrow>=14.0.0; extra == "processing"
Provides-Extra: dev
Requires-Dist: pytest>=7.0.0; extra == "dev"
Requires-Dist: pytest-cov>=4.0.0; extra == "dev"
Requires-Dist: pytest-mock>=3.10.0; extra == "dev"
Requires-Dist: black>=23.0.0; extra == "dev"
Requires-Dist: isort>=5.12.0; extra == "dev"
Requires-Dist: flake8>=6.0.0; extra == "dev"
Requires-Dist: mypy>=1.0.0; extra == "dev"
Requires-Dist: pre-commit>=3.0.0; extra == "dev"
Provides-Extra: docs
Requires-Dist: sphinx>=6.0.0; extra == "docs"
Requires-Dist: sphinx-rtd-theme>=1.2.0; extra == "docs"
Requires-Dist: myst-parser>=2.0.0; extra == "docs"
Provides-Extra: all
Requires-Dist: sm-dag-compiler[nlp,processing,pytorch,xgboost]; extra == "all"
Dynamic: license-file
